pyrism/__init__.py
pyrism/core/__init__.py
pyrism/core/_core.py
pyrism/core/auxiliary.py
pyrism/models/__init__.py
pyrism/models/library.py
pyrism/models/models.py
pyrism-0.0.1.1.dist-info/DESCRIPTION.rst
pyrism-0.0.1.1.dist-info/METADATA
pyrism-0.0.1.1.dist-info/RECORD
pyrism-0.0.1.1.dist-info/WHEEL
pyrism-0.0.1.1.dist-info/metadata.json
pyrism-0.0.1.1.dist-info/top_level.txt
