Metadata-Version: 2.0
Name: pyrism
Version: 0.0.1.1
Summary: Python bindings for Remote Sensing Models
Home-page: https://github.com/ibaris/pyrism
Author: Ismail Baris
Maintainer: Ismail Baris
License: UNKNOWN
Keywords: radar,remote-sensing,optics,integration,microwave,estimation,physics,radiative transfer
Platform: UNKNOWN
Classifier: Intended Audience :: Science/Research
Classifier: Topic :: Scientific/Engineering :: Atmospheric Science
Classifier: License :: OSI Approved :: MIT License
Classifier: Programming Language :: Python :: 2.7
Classifier: Operating System :: Microsoft
Requires-Dist: numpy
Requires-Dist: scipy
